{
  "type": "Compass Connections",
  "version": {
    "$numberInt": "1"
  },
  "connections": [
    {
      "id": "0499abf6-a531-4437-9162-3a0590cece42",
      "lastUsed": {
        "$date": {
          "$numberLong": "1733837911498"
        }
      },
      "favorite": {
        "name": "mongo"
      },
      "savedConnectionType": "recent",
      "connectionOptions": {
        "connectionString": "mongodb://localhost:27017/",
        "oidc": {
          "serializedState": "eyJvaWRjUGx1Z2luU3RhdGVWZXJzaW9uIjowLCJzdGF0ZSI6W119"
        }
      }
    }
  ]
}